TongguoLiziXuexiGoWebBiancheng/README.md
TongguoLiziXuexiGoWebBiancheng/__init__.py
TongguoLiziXuexiGoWebBiancheng/__main__.py
TongguoLiziXuexiGoWebBiancheng/file.epub
TongguoLiziXuexiGoWebBiancheng/index.html
TongguoLiziXuexiGoWebBiancheng/css/__init__.py
TongguoLiziXuexiGoWebBiancheng/css/annotations.css
TongguoLiziXuexiGoWebBiancheng/css/main.css
TongguoLiziXuexiGoWebBiancheng/css/normalize.css
TongguoLiziXuexiGoWebBiancheng/css/popup.css
TongguoLiziXuexiGoWebBiancheng/font/__init__.py
TongguoLiziXuexiGoWebBiancheng/font/fontello.eot
TongguoLiziXuexiGoWebBiancheng/font/fontello.svg
TongguoLiziXuexiGoWebBiancheng/font/fontello.ttf
TongguoLiziXuexiGoWebBiancheng/font/fontello.woff
TongguoLiziXuexiGoWebBiancheng/img/__init__.py
TongguoLiziXuexiGoWebBiancheng/img/annotator-glyph-sprite.png
TongguoLiziXuexiGoWebBiancheng/img/annotator-icon-sprite.png
TongguoLiziXuexiGoWebBiancheng/img/apple-touch-icon.png
TongguoLiziXuexiGoWebBiancheng/img/cancelfullscreen.png
TongguoLiziXuexiGoWebBiancheng/img/close.png
TongguoLiziXuexiGoWebBiancheng/img/fullscreen.png
TongguoLiziXuexiGoWebBiancheng/img/loader.gif
TongguoLiziXuexiGoWebBiancheng/img/menu-icon.png
TongguoLiziXuexiGoWebBiancheng/img/save.png
TongguoLiziXuexiGoWebBiancheng/img/saved.png
TongguoLiziXuexiGoWebBiancheng/img/settings-s.png
TongguoLiziXuexiGoWebBiancheng/img/settings.png
TongguoLiziXuexiGoWebBiancheng/img/star.png
TongguoLiziXuexiGoWebBiancheng/js/__init__.py
TongguoLiziXuexiGoWebBiancheng/js/epub.js
TongguoLiziXuexiGoWebBiancheng/js/epub.min.js
TongguoLiziXuexiGoWebBiancheng/js/epub.min.map
TongguoLiziXuexiGoWebBiancheng/js/hooks.min.js
TongguoLiziXuexiGoWebBiancheng/js/hooks.min.map
TongguoLiziXuexiGoWebBiancheng/js/reader.js
TongguoLiziXuexiGoWebBiancheng/js/reader.js.map
TongguoLiziXuexiGoWebBiancheng/js/reader.min.js
TongguoLiziXuexiGoWebBiancheng/js/reader.min.map
TongguoLiziXuexiGoWebBiancheng/js/hooks/__init__.py
TongguoLiziXuexiGoWebBiancheng/js/hooks/extensions/__init__.py
tongguo_lizi_xuexi_go_web_biancheng-2024.3.2.0.dist-info/METADATA
tongguo_lizi_xuexi_go_web_biancheng-2024.3.2.0.dist-info/WHEEL
tongguo_lizi_xuexi_go_web_biancheng-2024.3.2.0.dist-info/entry_points.txt
tongguo_lizi_xuexi_go_web_biancheng-2024.3.2.0.dist-info/top_level.txt
tongguo_lizi_xuexi_go_web_biancheng-2024.3.2.0.dist-info/RECORD
